jupyter_apache_zeppelin_proxy/__init__.py
jupyter_apache_zeppelin_proxy/icons/zeppelin.svg
jupyter_apache_zeppelin_proxy-1.0.5.dist-info/LICENSE.md
jupyter_apache_zeppelin_proxy-1.0.5.dist-info/METADATA
jupyter_apache_zeppelin_proxy-1.0.5.dist-info/WHEEL
jupyter_apache_zeppelin_proxy-1.0.5.dist-info/entry_points.txt
jupyter_apache_zeppelin_proxy-1.0.5.dist-info/top_level.txt
jupyter_apache_zeppelin_proxy-1.0.5.dist-info/RECORD
