Metadata-Version: 2.1
Name: jupyter-apache-zeppelin-proxy
Version: 1.0.5
Summary: Jupyter Server Proxy for Apache Zeppelin
Home-page: https://github.com/tiaden/jupyter-apache-zeppelin-proxy
Author: Edem Tiassou
Author-email: workmail.edem@gmail.com
License: MIT LICENSE
Keywords: Jupyter,Jupyter Proxy,Jupyter Server Proxy,Apache Zeppelin Integration for Jupyter,Apache Zeppelin,Apache Zeppelin Proxy
Classifier: Framework :: Jupyter
Classifier: Intended Audience :: Developers
Classifier: Natural Language :: English
Classifier: Programming Language :: Python
Classifier: Programming Language :: Python :: 3.8
Classifier: Programming Language :: Python :: 3.9
Classifier: Programming Language :: Python :: 3.10
Requires-Python: ~=3.8
License-File: LICENSE.md
Requires-Dist: jupyter-server-proxy
Provides-Extra: dev
Requires-Dist: black ; extra == 'dev'
Requires-Dist: ruamel.yaml ; extra == 'dev'
Requires-Dist: pytest ; extra == 'dev'
Requires-Dist: pytest-cov ; extra == 'dev'
